README.rst
setup.py
PyAccessPoint/__init__.py
PyAccessPoint/main.py
PyAccessPoint/pyaccesspoint.py
PyAccessPoint.egg-info/PKG-INFO
PyAccessPoint.egg-info/SOURCES.txt
PyAccessPoint.egg-info/dependency_links.txt
PyAccessPoint.egg-info/entry_points.txt
PyAccessPoint.egg-info/requires.txt
PyAccessPoint.egg-info/top_level.txt