Metadata-Version: 1.0
Name: PyAccessPoint
Version: 0.1.0
Summary: Package to manage wifi hotspot on linux
Home-page: https://github.com/Goblenus/pyaccesspoint
Author: Anton Bautkin
Author-email: antonbautkin@gmail.com
License: GNU GPLv3
Platform: UNKNOWN
